musiccli/__init__.py
musiccli/__main__.py
musiccli/crawler.py
musiccli/main.py
musiccli-1.2.0.dist-info/LICENSE.txt
musiccli-1.2.0.dist-info/METADATA
musiccli-1.2.0.dist-info/WHEEL
musiccli-1.2.0.dist-info/entry_points.txt
musiccli-1.2.0.dist-info/top_level.txt
musiccli-1.2.0.dist-info/RECORD
